calabar/__init__.py
calabar/arch.py
calabar/driveutils.py
calabar/install.py
calabar/notifications.py
calabar/utils.py
calabar-0.1.0.dist-info/LICENSE
calabar-0.1.0.dist-info/METADATA
calabar-0.1.0.dist-info/WHEEL
calabar-0.1.0.dist-info/top_level.txt
calabar-0.1.0.dist-info/RECORD
