Metadata-Version: 2.1
Name: calabar
Version: 0.1.0
Summary: Collection of Useful Tools for Google Colab.
Author-email: Taras Savchyn <trsvchn@gmail.com>
License: Apache License
Requires-Python: >=3.6
License-File: LICENSE
Requires-Dist: pydrive
